{
    "name": "Spotřební koš - Billa",
    "items": [
        {
            "store": "billa",
            "id": "82-352174",
            "name": "Vepřová pečeně bez kosti",
            "category": "31",
            "price": 219.9,
            "isWeighted": false,
            "unit": "g",
            "quantity": 1000,
            "bio": false,
            "available": true,
            "url": "https://shop.billa.cz/produkt/veprova-pecene-bez-kosti-82352174"
        },
        {
            "store": "billa",
            "id": "82-314894",
            "name": "clever Mléko polotučné trvanlivé 1,5 % tuku 1l",
            "category": "21",
            "price": 18.9,
            "isWeighted": false,
            "unit": "ml",
            "quantity": 1000,
            "bio": false,
            "available": true,
            "url": "https://shop.billa.cz/produkt/clever-mleko-polotucne-trvanlive-15-tuku-1l-82314894"
        },
        {
            "store": "billa",
            "id": "82-317178",
            "name": "Billa Eidam 30% krájený, plátky",
            "category": "20",
            "price": 199,
            "isWeighted": true,
            "unit": "g",
            "quantity": 1000,
            "bio": false,
            "available": true,
            "url": "https://shop.billa.cz/produkt/billa-eidam-30-krajeny-platky-82317178"
        },
        {
            "store": "billa",
            "id": "82-234812",
            "name": "Olma Klasik originál bílý jogurt 150g",
            "category": "23",
            "price": 7.9,
            "isWeighted": false,
            "unit": "g",
            "quantity": 150,
            "bio": false,
            "available": true,
            "url": "https://shop.billa.cz/produkt/olma-klasik-original-bily-jogurt-150g-82234812"
        },
        {
            "store": "billa",
            "id": "82-315500",
            "name": "BILLA Čerstvá vejce M 10 ks",
            "category": "29",
            "price": 47.9,
            "isWeighted": false,
            "unit": "kus",
            "quantity": 10,
            "bio": false,
            "available": true,
            "url": "https://shop.billa.cz/produkt/billa-cerstva-vejce-m-10-ks-82315500"
        },
        {
            "store": "billa",
            "id": "82-204112",
            "name": "Madeta Jihočeské máslo 250g",
            "category": "22",
            "price": 47.9,
            "isWeighted": false,
            "unit": "g",
            "quantity": 250,
            "bio": false,
            "available": true,
            "url": "https://shop.billa.cz/produkt/madeta-jihoceske-maslo-250g-82204112"
        },
        {
            "store": "billa",
            "id": "82-270690",
            "name": "clever Pšeničná mouka hladká 1kg",
            "category": "68",
            "price": 16.9,
            "isWeighted": false,
            "unit": "g",
            "quantity": 1000,
            "bio": false,
            "available": true,
            "url": "https://shop.billa.cz/produkt/clever-psenicna-mouka-hladka-1kg-82270690"
        },
        {
            "store": "billa",
            "id": "82-316365",
            "name": "Chléb konzumní s kmínem",
            "category": "10",
            "price": 42.5,
            "isWeighted": false,
            "unit": "g",
            "quantity": 1000,
            "bio": false,
            "available": true,
            "url": "https://shop.billa.cz/produkt/chleb-konzumni-s-kminem-82316365"
        },
        {
            "store": "billa",
            "id": "82-316363",
            "name": "Rohlík 43g",
            "category": "11",
            "price": 2.7,
            "isWeighted": false,
            "unit": "g",
            "quantity": 1000,
            "bio": false,
            "available": true,
            "url": "https://shop.billa.cz/produkt/rohlik-43g-82316363"
        },
        {
            "store": "billa",
            "id": "82-284151",
            "name": "Cukr krystal 1 kg",
            "category": "68",
            "price": 26.9,
            "isWeighted": false,
            "unit": "g",
            "quantity": 1000,
            "bio": false,
            "available": true,
            "url": "https://shop.billa.cz/produkt/cukr-krystal-1-kg-82284151"
        },
        {
            "store": "billa",
            "id": "82-169664",
            "name": "Budvar Výčepní světlé výčepní pivo lahev 0,5l",
            "category": "80",
            "price": 17.9,
            "isWeighted": false,
            "unit": "ml",
            "quantity": 500,
            "bio": false,
            "available": true,
            "url": "https://shop.billa.cz/produkt/budvar-vycepni-svetle-vycepni-pivo-lahev-05l-82169664"
        },
        {
            "store": "billa",
            "id": "82-304444",
            "name": "Brambory konzumní rané",
            "category": "01",
            "price": 29.9,
            "isWeighted": true,
            "unit": "g",
            "quantity": 1000,
            "bio": false,
            "available": true,
            "url": "https://shop.billa.cz/produkt/brambory-konzumni-rane-82304444"
        },
        {
            "store": "billa",
            "id": "82-230466",
            "name": "Jablko červené volné",
            "category": "00",
            "price": 34.9,
            "isWeighted": false,
            "unit": "g",
            "quantity": 1000,
            "bio": false,
            "available": true,
            "url": "https://shop.billa.cz/produkt/jablko-cervene-volne-82230466"
        }
    ]
}
